dbbasic_queue/__init__.py
dbbasic_queue/queue.py
dbbasic_queue-1.0.0.dist-info/licenses/LICENSE
dbbasic_queue-1.0.0.dist-info/METADATA
dbbasic_queue-1.0.0.dist-info/WHEEL
dbbasic_queue-1.0.0.dist-info/top_level.txt
dbbasic_queue-1.0.0.dist-info/RECORD
