Metadata-Version: 2.4
Name: dbbasic-queue
Version: 1.0.0
Summary: TSV-based job queue for async tasks
Home-page: https://github.com/askrobots/dbbasic-queue
Author: DBBasic Project
Author-email: dan@quellhorst.com
Project-URL: Bug Tracker, https://github.com/askrobots/dbbasic-queue/issues
Project-URL: Documentation, https://github.com/askrobots/dbbasic-queue#readme
Project-URL: Source Code, https://github.com/askrobots/dbbasic-queue
Project-URL: Specification, http://dbbasic.com/queue-spec
Keywords: queue,job queue,background jobs,async,tsv,cron,worker
Classifier: Development Status :: 4 - Beta
Classifier: Intended Audience :: Developers
Classifier: Topic :: Software Development :: Libraries :: Python Modules
Classifier: Topic :: System :: Distributed Computing
Classifier: License :: OSI Approved :: MIT License
Classifier: Programming Language :: Python :: 3
Classifier: Programming Language :: Python :: 3.6
Classifier: Programming Language :: Python :: 3.7
Classifier: Programming Language :: Python :: 3.8
Classifier: Programming Language :: Python :: 3.9
Classifier: Programming Language :: Python :: 3.10
Classifier: Programming Language :: Python :: 3.11
Classifier: Programming Language :: Python :: 3.12
Classifier: Operating System :: OS Independent
Requires-Python: >=3.6
License-File: LICENSE
Provides-Extra: dev
Requires-Dist: pytest>=7.0.0; extra == "dev"
Requires-Dist: pytest-cov>=4.0.0; extra == "dev"
Dynamic: author
Dynamic: author-email
Dynamic: classifier
Dynamic: description
Dynamic: description-content-type
Dynamic: home-page
Dynamic: keywords
Dynamic: license-file
Dynamic: project-url
Dynamic: provides-extra
Dynamic: requires-python
Dynamic: summary
